emergence_engine/__init__.py
emergence_engine/cli.py
emergence_engine/emergence.py
emergence_engine/engine.py
emergence_engine/grammar.py
emergence_engine/mdl.py
emergence_engine/repair.py
emergence_engine/sequitur.py
emergence_engine/symbols.py
emergence_engine/tokenizer.py
emergence_engine/viz.py
ufr_ds/__init__.py
ufr_ds/cli.py
ufr_ds/engine_suggest.py
ufr_ds/families.py
ufr_ds/generator.py
ufr_ds/llm.py
ufr_ds/react_tokenizer.py
ufr_ds/report.py
ufr_ds/tokenizer_node_bridge.py
ufr_ds-0.1.1.dist-info/licenses/LICENSE
ufr_ds-0.1.1.dist-info/METADATA
ufr_ds-0.1.1.dist-info/WHEEL
ufr_ds-0.1.1.dist-info/entry_points.txt
ufr_ds-0.1.1.dist-info/top_level.txt
ufr_ds-0.1.1.dist-info/RECORD
