Metadata-Version: 2.4
Name: ufr-ds
Version: 0.1.1
Summary: UFR Design System analyzer and generator (Emergence Engine–powered)
Author-email: UFR <dev@ufr.example>
License: MIT
Project-URL: Homepage, https://github.com/wespiper/ufr-ds
Project-URL: Repository, https://github.com/wespiper/ufr-ds
Project-URL: Issues, https://github.com/wespiper/ufr-ds/issues
Requires-Python: >=3.9
License-File: LICENSE
Dynamic: license-file
